speedyibl/__init__.py
speedyibl/speedyibl.py
speedyibl/speedyibl1_9.py
speedyibl_tutorial/GridWorld_Scenario1.py
speedyibl_tutorial/Gridworld_Scenario2.py
speedyibl_tutorial/Gridworld_Scenario3.py
speedyibl_tutorial/__init__.py
speedyibl_tutorial/speedyibl.py
speedyibl-0.2.3.dist-info/METADATA
speedyibl-0.2.3.dist-info/WHEEL
speedyibl-0.2.3.dist-info/top_level.txt
speedyibl-0.2.3.dist-info/RECORD
