Metadata-Version: 2.1
Name: speedyibl
Version: 0.2.3
Summary: Speedy implementation of IBL (Instance-based Learning)
Home-page: UNKNOWN
Author: Nhat Phan
Author-email: <nhatsp@gmail.com
License: Free for research purposes
Keywords: Decision Making,Instance-based Learning,Cognitive Model
Platform: UNKNOWN
Classifier: Intended Audience :: Science/Research
Classifier: Programming Language :: Python :: 3
Classifier: Operating System :: MacOS :: MacOS X
Classifier: Operating System :: Microsoft :: Windows
